hydroutils/__init__.py
hydroutils/hydro_arithmetric.py
hydroutils/hydro_file.py
hydroutils/hydro_log.py
hydroutils/hydro_plot.py
hydroutils/hydro_s3.py
hydroutils/hydro_stat.py
hydroutils/hydro_time.py
hydroutils-0.0.14.dist-info/AUTHORS.rst
hydroutils-0.0.14.dist-info/LICENSE
hydroutils-0.0.14.dist-info/METADATA
hydroutils-0.0.14.dist-info/WHEEL
hydroutils-0.0.14.dist-info/dependency_links.txt
hydroutils-0.0.14.dist-info/entry_points.txt
hydroutils-0.0.14.dist-info/top_level.txt
hydroutils-0.0.14.dist-info/RECORD
