Metadata-Version: 2.1
Name: hydroutils
Version: 0.0.14
Summary: A collection of commonly used util functions in hydrological modeling
Home-page: https://github.com/OuyangWenyu/hydroutils
Author: Wenyu Ouyang
Author-email: wenyuouyang@outlook.com
License: MIT license
Keywords: hydroutils
Classifier: Development Status :: 2 - Pre-Alpha
Classifier: Intended Audience :: Developers
Classifier: License :: OSI Approved :: MIT License
Classifier: Natural Language :: English
Classifier: Programming Language :: Python :: 3
Classifier: Programming Language :: Python :: 3.9
Classifier: Programming Language :: Python :: 3.10
Requires-Python: >=3.9
License-File: LICENSE
License-File: AUTHORS.rst
Requires-Dist: numpy
Requires-Dist: pandas
Requires-Dist: matplotlib
Requires-Dist: seaborn
Requires-Dist: cartopy
Requires-Dist: HydroErr
Requires-Dist: async-retriever
Requires-Dist: tqdm
Requires-Dist: rich
Requires-Dist: boto3~=1.34.34
Requires-Dist: minio
Requires-Dist: s3fs~=2024.2
Requires-Dist: tzfpy
